{
  "audio": "https://www.dropbox.com/s/b8h8s8c4qfquc0b/changed.wav",
  "words": [
    {
      "duration": 1.1,
      "text": "متن ساختگی",
      "person": "Ali"
    },
    {
      "duration": 1.2,
      "text": "ویرایش شده",
      "person": "Ali"
    },
    {
      "duration": 1,
      "text": "با تولید سادگی",
      "person": "Ali"
    },
    {
      "duration": 1.4,
      "text": "نامفهوم از صنعت",
      "person": "Ali"
    },
    {
      "duration": 1.5,
      "text": "چاپ و با استفاده",
      "person": "Ali"
    },
    {
      "duration": 1,
      "text": "از طراحان",
      "person": "Ali"
    },
    {
      "duration": 1.3,
      "text": "گرافیک است.",
      "person": "Ali"
    },
    {
      "duration": 2,
      "text": "چاپگرها و متون بلکه",
      "person": "Mohammad"
    },
    {
      "duration": 1,
      "text": "روزنامه و مجله",
      "person": "Mohammad"
    },
    {
      "duration": 1,
      "text": "در ستون و سطر",
      "person": "Mohammad"
    },
    {
      "duration": 1.8,
      "text": "آنچنان که لازم است",
      "person": "Mohammad"
    },
    {
      "duration": 1.8,
      "text": "و برای شرایط فعلی",
      "person": "Mohammad"
    },
    {
      "duration": 1.7,
      "text": "تکنولوژی مورد نیاز",
      "person": "Mohammad"
    },
    {
      "duration": 1.4,
      "text": "و کاربردهای متنوع",
      "person": "Mohammad"
    },
    {
      "duration": 1,
      "text": "با هدف بهبود",
      "person": "Mohammad"
    },
    {
      "duration": 3.4,
      "text": "ابزارهای کاربردی می باشد.",
      "person": "Mohammad"
    },
    {
      "duration": 1.4,
      "text": "کتابهای زیادی در",
      "person": "Ali"
    },
    {
      "duration": 1.2,
      "text": "شصت و سه درصد",
      "person": "Ali"
    },
    {
      "duration": 2,
      "text": "گذشته، حال و آینده",
      "person": "Ali"
    },
    {
      "duration": 1.8,
      "text": "شناخت فراوان جامعه",
      "person": "Ali"
    },
    {
      "duration": 1.8,
      "text": "و متخصصان را می طلبد",
      "person": "Ali"
    },
    {
      "duration": 1.6,
      "text": "تا با نرم افزارها",
      "person": "Ali"
    },
    {
      "duration": 1,
      "text": "شناخت بیشتری را",
      "person": "Ali"
    },
    {
      "duration": 1.8,
      "text": "برای طراحان رایانه ای",
      "person": "Ali"
    },
    {
      "duration": 1.5,
      "text": "علی الخصوص طراحان",
      "person": "Ali"
    },
    {
      "duration": 1.8,
      "text": "خلاقی و فرهنگ پیشرو",
      "person": "Ali"
    },
    {
      "duration": 1,
      "text": "در زبان فارسی",
      "person": "Ali"
    },
    {
      "duration": 1.2,
      "text": "ایجاد کرد.",
      "person": "Ali"
    },
    {
      "duration": 1,
      "text": "در این صورت",
      "person": "Mohammad"
    },
    {
      "duration": 1,
      "text": "می توان امید داشت",
      "person": "Mohammad"
    },
    {
      "duration": 1.7,
      "text": "که تمام و دشواری",
      "person": "Mohammad"
    },
    {
      "duration": 1,
      "text": "موجود در ارائه",
      "person": "Mohammad"
    },
    {
      "duration": 1.5,
      "text": "راهکارها و شرایط",
      "person": "Mohammad"
    },
    {
      "duration": 0.8,
      "text": "سخت تایپ",
      "person": "Mohammad"
    },
    {
      "duration": 1,
      "text": "به پایان رسد",
      "person": "Mohammad"
    },
    {
      "duration": 1.4,
      "text": "وزمان مورد نیاز",
      "person": "Mohammad"
    },
    {
      "duration": 1.3,
      "text": "شامل حروفچینی",
      "person": "Mohammad"
    },
    {
      "duration": 1.4,
      "text": "دستاوردهای اصلی",
      "person": "Mohammad"
    },
    {
      "duration": 1.4,
      "text": "و جوابگوی سوالات",
      "person": "Mohammad"
    },
    {
      "duration": 1.2,
      "text": "پیوسته اهل",
      "person": "Mohammad"
    },
    {
      "duration": 1,
      "text": "دنیای موجود",
      "person": "Mohammad"
    },
    {
      "duration": 1.1,
      "text": "طراحی اساسا",
      "person": "Mohammad"
    },
    {
      "duration": 1,
      "text": "مورد استفاده",
      "person": "Mohammad"
    },
    {
      "duration": 1.4,
      "text": "قرار گیرد.",
      "person": "Mohammad"
    }
  ]
}